{
    "zone": {
        "identifier": "alliance-zone12",
        "camera_left_url": "http://alliance-zone12-camera01.ccis.ualberta.ca:8080/observation",
        "camera_right_url": null,
        "lightbar_url": "http://142.244.191.37:8080/action",
        "calibration": {
            "action": [
                0.2,
                0.25,
                0.3,
                0.35,
                0.4,
                0.5,
                0.6,
                0.7,
                0.8,
                0.85,
                0.9,
                0.95,
                1
            ],
            "blue": [
                0.0,
                1.0,
                6.0,
                14.0,
                23.0,
                41.0,
                58.0,
                75.0,
                90.0,
                98.0,
                104.0,
                111.0,
                117
            ],
            "cool_white": [
                0.0,
                0.0,
                5.0,
                12.0,
                21.0,
                37.0,
                54.0,
                70.0,
                84.0,
                91.0,
                98.0,
                105.0,
                111
            ],
            "warm_white": [
                0.0,
                0.0,
                3.0,
                9.0,
                17.0,
                31.0,
                44.0,
                57.0,
                69.0,
                74.0,
                79.0,
                82.0,
                85
            ],
            "orange_red": [
                0.0,
                0.0,
                5.0,
                12.0,
                20.0,
                37.0,
                54.0,
                70.0,
                84.0,
                92.0,
                96.0,
                98.0,
                98
            ],
            "red": [
                0.0,
                0.0,
                4.0,
                10.0,
                16.0,
                30.0,
                42.0,
                54.0,
                67.0,
                71.0,
                74.0,
                75.0,
                75
            ],
            "far_red": [
                0.0,
                0.057206500000000944,
                1.3861765000000015,
                3.5572930000000005,
                6.023851999999999,
                10.848707499999998,
                15.537915499999993,
                19.908463499999986,
                23.911526999999985,
                25.624945499999995,
                26.941244499999986,
                27.568404499999986,
                27.761256999999983
            ]
        },
        "trays": [
            {
                "n_wide": 6,
                "n_tall": 3,
                "rect": {
                    "top_left": [
                        230,
                        381
                    ],
                    "top_right": [
                        1504,
                        298
                    ],
                    "bottom_left": [
                        218,
                        1006
                    ],
                    "bottom_right": [
                        1528,
                        976
                    ]
                }
            },
            {
                "n_wide": 6,
                "n_tall": 3,
                "rect": {
                    "top_left": [
                        204,
                        1081
                    ],
                    "top_right": [
                        1509,
                        1049
                    ],
                    "bottom_left": [
                        269,
                        1713
                    ],
                    "bottom_right": [
                        1526,
                        1710
                    ]
                }
            }
        ]
    }
}
